pgwait.py
wait_for_postgres.py
pgwait-0.3.dist-info/DESCRIPTION.rst
pgwait-0.3.dist-info/METADATA
pgwait-0.3.dist-info/RECORD
pgwait-0.3.dist-info/WHEEL
pgwait-0.3.dist-info/entry_points.txt
pgwait-0.3.dist-info/metadata.json
pgwait-0.3.dist-info/top_level.txt
